odoo/addons/purchase_order_line_invoicing/README.rst
odoo/addons/purchase_order_line_invoicing/__init__.py
odoo/addons/purchase_order_line_invoicing/__manifest__.py
odoo/addons/purchase_order_line_invoicing/i18n/es.po
odoo/addons/purchase_order_line_invoicing/i18n/it.po
odoo/addons/purchase_order_line_invoicing/i18n/purchase_order_line_invoicing.pot
odoo/addons/purchase_order_line_invoicing/models/__init__.py
odoo/addons/purchase_order_line_invoicing/models/res_partner.py
odoo/addons/purchase_order_line_invoicing/readme/CONTRIBUTORS.rst
odoo/addons/purchase_order_line_invoicing/readme/DESCRIPTION.rst
odoo/addons/purchase_order_line_invoicing/readme/USAGE.rst
odoo/addons/purchase_order_line_invoicing/security/purchase_order_line_invoice_details.xml
odoo/addons/purchase_order_line_invoicing/security/purchase_order_line_invoice_wizard.xml
odoo/addons/purchase_order_line_invoicing/static/description/icon.png
odoo/addons/purchase_order_line_invoicing/static/description/index.html
odoo/addons/purchase_order_line_invoicing/tests/__init__.py
odoo/addons/purchase_order_line_invoicing/tests/test_purchase_order_line_invoicing_wizard.py
odoo/addons/purchase_order_line_invoicing/views/res_partner_views.xml
odoo/addons/purchase_order_line_invoicing/wizards/__init__.py
odoo/addons/purchase_order_line_invoicing/wizards/purchase_order_line_invoice_details.py
odoo/addons/purchase_order_line_invoicing/wizards/purchase_order_line_invoicing_wizard.py
odoo/addons/purchase_order_line_invoicing/wizards/purchase_order_line_invoicing_wizard.xml
odoo14_addon_purchase_order_line_invoicing-14.0.1.0.1.dev12.dist-info/METADATA
odoo14_addon_purchase_order_line_invoicing-14.0.1.0.1.dev12.dist-info/WHEEL
odoo14_addon_purchase_order_line_invoicing-14.0.1.0.1.dev12.dist-info/top_level.txt
odoo14_addon_purchase_order_line_invoicing-14.0.1.0.1.dev12.dist-info/RECORD
